df4loop/__init__.py
df4loop/df4loop.py
tests/__init__.py
tests/test_df4loop.py
df4loop-0.1.0.dist-info/LICENSE
df4loop-0.1.0.dist-info/METADATA
df4loop-0.1.0.dist-info/WHEEL
df4loop-0.1.0.dist-info/top_level.txt
df4loop-0.1.0.dist-info/RECORD
