Metadata-Version: 2.1
Name: df4loop
Version: 0.1.0
Summary: df4loop supports general purpose processe that requires a combination of both pandas.DataFrame and loop.
Home-page: https://github.com/daikikatsuragawa/df4loop
Author: Daiki Katsuragawa
Author-email: daikikatsuragawa@gmail.com
License: Apache-2.0
Platform: UNKNOWN
Classifier: Programming Language :: Python :: 3
Classifier: License :: OSI Approved :: Apache Software License
Classifier: Operating System :: OS Independent
Requires-Python: >=3.7
Requires-Dist: pandas (>=1.0.0)
